disk/Box.py
disk/Buffer.py
disk/Cache.py
disk/HardFolder.py
disk/NestedBoxes.py
disk/Path.py
disk/__init__.py
disk/exceptions.py
disk/get_creation_date.py
disk/individual_functions.py
disk/pickle_function.py
disk/zip.py
disk-2021.6.29.dist-info/LICENSE
disk-2021.6.29.dist-info/METADATA
disk-2021.6.29.dist-info/WHEEL
disk-2021.6.29.dist-info/top_level.txt
disk-2021.6.29.dist-info/RECORD
