Metadata-Version: 2.1
Name: disk
Version: 2021.6.29
Summary: Python library for interacting with the file system
Home-page: https://github.com/idin/disk
Author: Idin
Author-email: py@idin.ca
License: MIT
Platform: UNKNOWN
Requires-Python: ~=3.6
